{
  "main": {
    "id": "dcff258b3b5eadca",
    "type": "split",
    "children": [
      {
        "id": "829d062b0af37a40",
        "type": "tabs",
        "children": [
          {
            "id": "b9b49246a036111f",
            "type": "leaf",
            "state": {
              "type": "canvas",
              "state": {
                "file": "GFX/UI.canvas",
                "viewState": {
                  "x": 2091.0842965782895,
                  "y": 130.4681170477753,
                  "zoom": -3.145452276865426
                }
              },
              "icon": "lucide-layout-dashboard",
              "title": "UI"
            }
          }
        ]
      }
    ],
    "direction": "vertical"
  },
  "left": {
    "id": "90e562c811c25852",
    "type": "split",
    "children": [
      {
        "id": "21e08ff91aeba409",
        "type": "tabs",
        "children": [
          {
            "id": "c0541ab0d6b7f0a5",
            "type": "leaf",
            "state": {
              "type": "file-explorer",
              "state": {
                "sortOrder": "alphabetical",
                "autoReveal": false
              },
              "icon": "lucide-folder-closed",
              "title": "Files"
            }
          },
          {
            "id": "c59182e55de26297",
            "type": "leaf",
            "state": {
              "type": "search",
              "state": {
                "query": "",
                "matchingCase": false,
                "explainSearch": false,
                "collapseAll": false,
                "extraContext": false,
                "sortOrder": "alphabetical"
              },
              "icon": "lucide-search",
              "title": "Search"
            }
          },
          {
            "id": "cc377fd9ddb0f47a",
            "type": "leaf",
            "state": {
              "type": "bookmarks",
              "state": {},
              "icon": "lucide-bookmark",
              "title": "Bookmarks"
            }
          }
        ]
      }
    ],
    "direction": "horizontal",
    "width": 300
  },
  "right": {
    "id": "70e7455a67bbd68e",
    "type": "split",
    "children": [
      {
        "id": "63d93f516b3f12f3",
        "type": "tabs",
        "children": [
          {
            "id": "25e5b04bc1b1ec00",
            "type": "leaf",
            "state": {
              "type": "backlink",
              "state": {
                "file": "GFX/Notes/KayKit - Character Animations.md",
                "collapseAll": false,
                "extraContext": false,
                "sortOrder": "alphabetical",
                "showSearch": false,
                "searchQuery": "",
                "backlinkCollapsed": false,
                "unlinkedCollapsed": true
              },
              "icon": "links-coming-in",
              "title": "Backlinks for KayKit - Character Animations"
            }
          },
          {
            "id": "0911a44322364aaf",
            "type": "leaf",
            "state": {
              "type": "outgoing-link",
              "state": {
                "file": "GFX/Notes/KayKit - Character Animations.md",
                "linksCollapsed": false,
                "unlinkedCollapsed": true
              },
              "icon": "links-going-out",
              "title": "Outgoing links from KayKit - Character Animations"
            }
          },
          {
            "id": "40bec3fa1cf833d6",
            "type": "leaf",
            "state": {
              "type": "tag",
              "state": {
                "sortOrder": "frequency",
                "useHierarchy": true,
                "showSearch": false,
                "searchQuery": ""
              },
              "icon": "lucide-tags",
              "title": "Tags"
            }
          },
          {
            "id": "1187e42961c848ea",
            "type": "leaf",
            "state": {
              "type": "outline",
              "state": {
                "file": "GFX/Notes/KayKit - Character Animations.md",
                "followCursor": false,
                "showSearch": false,
                "searchQuery": ""
              },
              "icon": "lucide-list",
              "title": "Outline of KayKit - Character Animations"
            }
          }
        ]
      }
    ],
    "direction": "horizontal",
    "width": 300,
    "collapsed": true
  },
  "left-ribbon": {
    "hiddenItems": {
      "switcher:Open quick switcher": false,
      "graph:Open graph view": false,
      "canvas:Create new canvas": false,
      "daily-notes:Open today's daily note": false,
      "templates:Insert template": false,
      "command-palette:Open command palette": false
    }
  },
  "active": "b9b49246a036111f",
  "lastOpenFiles": [
    "GFX/Shaders.canvas",
    "GFX/GFX.md",
    "GFX/UI.canvas",
    "GFX/Notes/Game Coins and Gems Pack.md",
    "GFX/Notes/Game Level Map Pack Horizontal Mode.md",
    "GFX/Resources/2D Pixel Quest Vol.3 The UI GUI.png",
    "Tutorials/Tutorials.md",
    "Tutorials/Programming/Complete Godot 3D Code Your Own 3D Games In Godot 4.md",
    "GFX/Notes/100 Illustrator Graphic Styles Bundle.md",
    "100 Illustrator Graphic Styles Bundle.png.md",
    "GFX/Notes/Christmas Icons GUI Pack.md",
    "GFX/Notes/Game Level Map Pack Horizontal Mode 2.md",
    "GFX/Notes/Flat Ability Icons.md",
    "GFX/Notes/Essential Inventory Sound Effects.md",
    "GFX/Notes/Captains GUI.md",
    "GFX/Notes/40 Fantasy Human Portraits.md",
    "GFX/Notes/40 Cute Portraits.md",
    "GFX/Notes/3D Dungeon Tileset & Asset Pack.md",
    "GFX/Notes/2D Pixel RPG Icon Pack.md",
    "GFX/Notes/2D Pixel Quest Vol.3 The UI GUI.md",
    "GFX/Notes/2D Icons Military Item.md",
    "GFX/Notes/2D Icons 150 Space Rank.md",
    "Link Collection.md",
    "Tutorials/Link collection.md",
    "Tutorials/Programming/Math For Video Games Build Better Games Faster With Advanced Game Math.md",
    "Tutorials/Programming/Unity 2D V2 - ARCHIVED COURSE.md",
    "Tutorials/Resources/Unity 2D V2 - ARCHIVED COURSE.png",
    "Tutorials/Programming/How To Get A Job In The Game Industry Create a Winning Resume, Portfolio, LinkedIn Profile & More.md",
    "Tutorials/Resources/How To Get A Job In The Game Industry Create a Winning Resume, Portfolio, LinkedIn Profile & More.png",
    "Tutorials/Programming/Unity RPG Core Combat Make Your Own RPG Combat System.md",
    "Tutorials/Resources/Unity RPG Core Combat Make Your Own RPG Combat System.png",
    "Tutorials/Resources/Finish It! - Tools & Techniques For Staying Motivated & Productive With Game Dev.png",
    "Tutorials/Resources/Get Git Smart Learn Git in Unity, SourceTree, GitHub.png",
    "Tutorials/Resources/Math For Video Games Build Better Games Faster With Advanced Game Math.png",
    "Tutorials/Resources/Unity RPG Inventory Systems Code Your Own RPG-Style Inventory.png",
    "Tutorials/Resources/Unity RPG Dialogue & Quests Create Your Own RPG Quest System with Dialog.png",
    "Tutorials/Resources/Unity Multiplayer Master Learn Unity Mirror to Build Your Own Multiplayer Tank Game.png",
    "GFX/Assets.canvas",
    "Tutorials/Resources",
    "GFX/Notes/todo.txt",
    "GFX/Notes/GUI Wooden 2.md.txt",
    "GFX/Notes/2D Icons 150 Space Rank.md.txt",
    "GFX/Notes/GUI Blue Sky.md.txt",
    "GFX/Notes/Brontes RPG MMO Game Interface.md.txt",
    "GFX/Notes/2D Pixel Quest Vol.3 The UI GUI.md.txt",
    "GFX/Notes/Halloween Party GUI Pack.md.txt",
    "GFX/Notes/Christmas Icons GUI Pack.md.txt",
    "GFX/Notes/60 RPG Spells and Ability Icons.md.txt"
  ]
}